mkdocs_ezlinks_plugin/__init__.py
mkdocs_ezlinks_plugin/file_mapper.py
mkdocs_ezlinks_plugin/plugin.py
mkdocs_ezlinks_plugin/replacer.py
mkdocs_ezlinks_plugin/types.py
mkdocs_ezlinks_plugin/scanners/__init__.py
mkdocs_ezlinks_plugin/scanners/base_link_scanner.py
mkdocs_ezlinks_plugin/scanners/md_link_scanner.py
mkdocs_ezlinks_plugin/scanners/reference_link_scanner.py
mkdocs_ezlinks_plugin/scanners/wiki_link_scanner.py
mkdocs_wikilinks_plugin-0.1.2.dist-info/licenses/LICENSE
mkdocs_wikilinks_plugin-0.1.2.dist-info/METADATA
mkdocs_wikilinks_plugin-0.1.2.dist-info/WHEEL
mkdocs_wikilinks_plugin-0.1.2.dist-info/entry_points.txt
mkdocs_wikilinks_plugin-0.1.2.dist-info/top_level.txt
mkdocs_wikilinks_plugin-0.1.2.dist-info/RECORD
