Metadata-Version: 2.4
Name: mkdocs-wikilinks-plugin
Version: 0.1.2
Summary: A mkdocs plugin that makes linking to other documents easy.
Home-page: https://github.com/carlos-truong/mkdocs-wikilinks-plugin
Author: Carlos
Author-email: carlos.truong.dev@gmail.com
License: MIT
Keywords: mkdocs,wikilinks,ezlinks,obsidian,roam
Classifier: Development Status :: 3 - Alpha
Classifier: Intended Audience :: Developers
Classifier: Intended Audience :: Information Technology
Classifier: Programming Language :: Python
Classifier: Programming Language :: Python :: 3 :: Only
Requires-Python: >=3.6
License-File: LICENSE
Requires-Dist: mkdocs
Requires-Dist: dataclasses>=0.7; python_version < "3.7.0"
Requires-Dist: pygtrie==2.*
Dynamic: author
Dynamic: author-email
Dynamic: classifier
Dynamic: description
Dynamic: description-content-type
Dynamic: home-page
Dynamic: keywords
Dynamic: license
Dynamic: license-file
Dynamic: requires-dist
Dynamic: requires-python
Dynamic: summary
